setup.cfg
setup.py
pithy/__init__.py
pithy/alarm.py
pithy/ansi.py
pithy/archive.py
pithy/buffer.py
pithy/clock.py
pithy/clonefile.py
pithy/collection.py
pithy/csv.py
pithy/date.py
pithy/default.py
pithy/defaultlist.py
pithy/desc.py
pithy/dict.py
pithy/dispatch.py
pithy/encode.py
pithy/encodings.py
pithy/eon.py
pithy/exceptions.py
pithy/fetch.py
pithy/filestatus.py
pithy/format.py
pithy/fs.py
pithy/graph.py
pithy/graphviz.py
pithy/interactive.py
pithy/io.py
pithy/iterable.py
pithy/json.py
pithy/lex.py
pithy/loader.py
pithy/markup.py
pithy/meta.py
pithy/msgpack.py
pithy/optional.py
pithy/parse.py
pithy/pat.py
pithy/path.py
pithy/path_encode.py
pithy/pickle.py
pithy/pipe.py
pithy/range.py
pithy/schema.py
pithy/sequence.py
pithy/sqlite.py
pithy/stdlib_info.py
pithy/string.py
pithy/svg.py
pithy/tag_parse.py
pithy/task.py
pithy/term.py
pithy/text_charts.py
pithy/transform.py
pithy/tree.py
pithy/types.py
pithy/typing.py
pithy/untyped.py
pithy/url.py
pithy/util.py
pithy/zst.py
pithy.egg-info/PKG-INFO
pithy.egg-info/SOURCES.txt
pithy.egg-info/dependency_links.txt
pithy.egg-info/top_level.txt
pithy/aws/__init__.py
pithy/aws/s3.py
pithy/diff/__init__.py
pithy/diff/patience.py
pithy/diff/util.py
pithy/html/__init__.py
pithy/html/loader.py
pithy/html/semantics.py
pithy/html/tree.py
pithy/http/__init__.py
pithy/http/server.py
pithy/py/__init__.py
pithy/py/lex.py
pithy/syntax/__init__.py
pithy/syntax/python.py
pithy/syntax/rst.py
pithy/unicode/__init__.py
pithy/unicode/categories.py
pithy/unicode/charsets.py
pithy/unicode/codepoints.py
pithy/unicode/data_09_00.py
pithy/unicode/data_10_00.py
pithy/unicode/data_11_00.py
pithy/xml/__init__.py
pithy/xml/escape.py
pithy/xml/generic.py
pithy/xml/tree.py